palette/__init__.py
palette/admin.py
palette/apps.py
palette/models.py
palette/tests.py
palette/views.py
palette/migrations/__init__.py
palette/static/admin/palette.css
palette/static/admin/palette.js
palette/templates/admin/base.html
django_command_palette-2022.11.25.dist-info/METADATA
django_command_palette-2022.11.25.dist-info/WHEEL
django_command_palette-2022.11.25.dist-info/top_level.txt
django_command_palette-2022.11.25.dist-info/RECORD
